bayesHC/__init__.py
bayesHC-0.0.1.dist-info/LICENSE
bayesHC-0.0.1.dist-info/METADATA
bayesHC-0.0.1.dist-info/WHEEL
bayesHC-0.0.1.dist-info/top_level.txt
bayesHC-0.0.1.dist-info/RECORD
